mydict/__init__.py
mydict/test_mydict.py
mydict/utils.py
mydict/jsonify/__init__.py
mydict-2.1.1.dist-info/licenses/LICENSE
mydict-2.1.1.dist-info/METADATA
mydict-2.1.1.dist-info/WHEEL
mydict-2.1.1.dist-info/top_level.txt
mydict-2.1.1.dist-info/RECORD
