Metadata-Version: 2.4
Name: mydict
Version: 2.1.1
Summary: A Python dict subclass which tries to act like JavaScript objects, so you can use the dot-notation (d.foo) to access members of the object.
Home-page: https://github.com/leon-domingo/mydict
Author: León Domingo
Author-email: leon.domingo@gmail.com
License: MIT
Keywords: dict javascript dot-notation
Classifier: Development Status :: 5 - Production/Stable
Classifier: Topic :: Utilities
License-File: LICENSE
Requires-Dist: stringcase
Provides-Extra: test
Requires-Dist: pytest; extra == "test"
Dynamic: author
Dynamic: author-email
Dynamic: classifier
Dynamic: description
Dynamic: description-content-type
Dynamic: home-page
Dynamic: keywords
Dynamic: license
Dynamic: license-file
Dynamic: provides-extra
Dynamic: requires-dist
Dynamic: summary
